polyapi-5.9.20.dist-info/licenses/LICENSE.txt
polymatica/__init__.py
polymatica/authorization.py
polymatica/business_logic_doc.py
polymatica/business_scenarios.py
polymatica/error_handler.py
polymatica/exceptions.py
polymatica/executor.py
polymatica/helper.py
polymatica/commands/__init__.py
polymatica/commands/base_command.py
polymatica/commands/olap_module.py
polymatica/commands/other_modules.py
polymatica/common/__init__.py
polymatica/common/consts.py
polymatica/common/helper_funcs.py
polymatica/common/params_models.py
polymatica/graph/__init__.py
polymatica/graph/base_graph.py
polymatica/graph/graph_interface.py
polymatica/graph/types/__init__.py
polymatica/graph/types/areas.py
polymatica/graph/types/balls.py
polymatica/graph/types/chord.py
polymatica/graph/types/circles.py
polymatica/graph/types/circles_series.py
polymatica/graph/types/corridors.py
polymatica/graph/types/cumulative_areas.py
polymatica/graph/types/cumulative_cylinders.py
polymatica/graph/types/cylinders.py
polymatica/graph/types/graph.py
polymatica/graph/types/lines.py
polymatica/graph/types/pies.py
polymatica/graph/types/point.py
polymatica/graph/types/point_series.py
polymatica/graph/types/pools.py
polymatica/graph/types/pools_3d.py
polymatica/graph/types/radar.py
polymatica/graph/types/sankey.py
polymatica/graph/types/surface.py
polyapi-5.9.20.dist-info/METADATA
polyapi-5.9.20.dist-info/WHEEL
polyapi-5.9.20.dist-info/top_level.txt
polyapi-5.9.20.dist-info/RECORD
