Metadata-Version: 2.4
Name: polyapi
Version: 5.9.20
Summary: Wrapper for Polymatica API
Home-page: https://slsoft.ru/products/polymatica/
Author: Polymatica Rus LLC
Author-email: polymatica_support@slsoft.ru
License: MIT
Keywords: polymatica
Classifier: Development Status :: 5 - Production/Stable
Classifier: Intended Audience :: End Users/Desktop
Classifier: Operating System :: OS Independent
Classifier: License :: OSI Approved :: MIT License
Classifier: Programming Language :: Python :: 3
License-File: LICENSE.txt
Requires-Dist: setuptools
Requires-Dist: numpy==1.19.5; python_version < "3.9"
Requires-Dist: numpy>1.21.1; python_version >= "3.9"
Requires-Dist: pandas<=1.2.5,>=1.1.5; python_version < "3.9"
Requires-Dist: pandas>2.0.0; python_version >= "3.9"
Requires-Dist: requests>=2.27.1
Requires-Dist: pydantic<=2.5.3,>=1.9.2
Requires-Dist: packaging
Dynamic: author
Dynamic: author-email
Dynamic: classifier
Dynamic: description
Dynamic: home-page
Dynamic: keywords
Dynamic: license
Dynamic: license-file
Dynamic: requires-dist
Dynamic: summary
